haiku_geometric/__init__.py
haiku_geometric/datasets/__init__.py
haiku_geometric/datasets/base.py
haiku_geometric/datasets/gnn_benchmark_dataset.py
haiku_geometric/datasets/karate_dataset.py
haiku_geometric/datasets/ogb_dataset.py
haiku_geometric/datasets/planetoid_dataset.py
haiku_geometric/datasets/toy_dataset.py
haiku_geometric/datasets/tu_dataset.py
haiku_geometric/datasets/utils.py
haiku_geometric/models/MLP.py
haiku_geometric/models/__init__.py
haiku_geometric/models/node2vec.py
haiku_geometric/nn/__init__.py
haiku_geometric/nn/aggr/__init__.py
haiku_geometric/nn/aggr/base.py
haiku_geometric/nn/aggr/basic.py
haiku_geometric/nn/aggr/degree_scaler.py
haiku_geometric/nn/aggr/multi.py
haiku_geometric/nn/aggr/utils.py
haiku_geometric/nn/attention/__init__.py
haiku_geometric/nn/attention/self_attention.py
haiku_geometric/nn/attention/transformer.py
haiku_geometric/nn/conv/__init__.py
haiku_geometric/nn/conv/edge_conv.py
haiku_geometric/nn/conv/gat_conv.py
haiku_geometric/nn/conv/gated_graph_conv.py
haiku_geometric/nn/conv/gcn_conv.py
haiku_geometric/nn/conv/general_conv.py
haiku_geometric/nn/conv/gin_conv.py
haiku_geometric/nn/conv/gine_conv.py
haiku_geometric/nn/conv/gps_layer.py
haiku_geometric/nn/conv/graph_conv.py
haiku_geometric/nn/conv/meta_layer.py
haiku_geometric/nn/conv/pna_conv.py
haiku_geometric/nn/conv/sage_conv.py
haiku_geometric/nn/conv/utils.py
haiku_geometric/nn/dense/__init__.py
haiku_geometric/nn/dense/linear.py
haiku_geometric/nn/pool/__init__.py
haiku_geometric/nn/pool/global_pool.py
haiku_geometric/nn/pool/topk_pool.py
haiku_geometric/posenc/__init__.py
haiku_geometric/posenc/laplacian_encoder.py
haiku_geometric/posenc/mag_laplacian_encoder.py
haiku_geometric/transforms/__init__.py
haiku_geometric/transforms/add_self_loops.py
haiku_geometric/transforms/normalize.py
haiku_geometric/transforms/remove_self_loops.py
haiku_geometric/utils/__init__.py
haiku_geometric/utils/batch.py
haiku_geometric/utils/coalesce.py
haiku_geometric/utils/laplacian.py
haiku_geometric-0.0.5.dist-info/METADATA
haiku_geometric-0.0.5.dist-info/WHEEL
haiku_geometric-0.0.5.dist-info/top_level.txt
haiku_geometric-0.0.5.dist-info/RECORD
