Metadata-Version: 2.1
Name: haiku-geometric
Version: 0.0.5
Summary: UNKNOWN
Home-page: https://github.com/alexOarga/haiku-geometric
Author: Alex Oarga
Author-email: alex718123@gmail.com
License: Apache-2.0 license
Platform: UNKNOWN
Classifier: Programming Language :: Python :: 3
Classifier: Operating System :: OS Independent
Requires-Dist: jax
Requires-Dist: dm-haiku
Requires-Dist: jraph
Requires-Dist: setuptools
Requires-Dist: tqdm
Requires-Dist: numba
